setup.cfg
setup.py
message_sender/__init__.py
message_sender/message_config.py
message_sender/message_engine.py
message_sender/message_manager.py
snowman_larch/__init__.py
snowman_larch.egg-info/PKG-INFO
snowman_larch.egg-info/SOURCES.txt
snowman_larch.egg-info/dependency_links.txt
snowman_larch.egg-info/top_level.txt
src/__init__.py