Metadata-Version: 2.1
Name: snowman-larch
Version: 2022.8.8.3
Summary: 落叶松
Home-page: https://...
Author: Alvin Zhang
Author-email: 18048587325@163.com
License: UNKNOWN
Platform: UNKNOWN
